README.md
audio_transformers/__init__.py
audio_transformers/cli/__init__.py
audio_transformers/cli/config.py
audio_transformers/cli/datasets/__init__.py
audio_transformers/cli/datasets/public.py
audio_transformers/cli/errors.py
audio_transformers/cli/handlers/__init__.py
audio_transformers/cli/handlers/datasets.py
audio_transformers/cli/handlers/root.py
audio_transformers/cli/handlers/transform.py
audio_transformers/cli/logconfig.py
audio_transformers/cli/task/__init__.py
audio_transformers/cli/task/errors.py
audio_transformers/cli/task/executor.py
audio_transformers/cli/task/initializers.py
audio_transformers/cli/task/model.py
audio_transformers/core/__init__.py
audio_transformers/core/band_pass.py
audio_transformers/core/band_stop.py
audio_transformers/core/composite.py
audio_transformers/core/gaussian_noise.py
audio_transformers/core/high_pass.py
audio_transformers/core/inversion.py
audio_transformers/core/low_pass.py
audio_transformers/core/model.py
audio_transformers/core/one_side_filter.py
audio_transformers/core/pitch_shift.py
audio_transformers/core/speed_perturbation.py
audio_transformers/core/transform.py
audio_transformers/core/two_side_filter.py
audio_transformers/io/__init__.py
audio_transformers/io/file.py
audio_transformers/io/format.py
audio_transformers/io/probe.py
audio_transformers/utils/__init__.py
audio_transformers/utils/archives.py
audio_transformers/utils/console.py
audio_transformers/utils/docs.py
audio_transformers/utils/types.py
audio_transformers/utils/urls.py
audio_transformers-1.0.0.dist-info/LICENSE
audio_transformers-1.0.0.dist-info/METADATA
audio_transformers-1.0.0.dist-info/WHEEL
audio_transformers-1.0.0.dist-info/entry_points.txt
audio_transformers-1.0.0.dist-info/RECORD
