Metadata-Version: 2.1
Name: audio-transformers
Version: 1.0.0
Summary: Audio data transformations library with a command-line interface.
Home-page: https://github.com/stepan-anokhin/audio-transformers
License: MIT
Author: Stepan Anokhin
Author-email: stepan.anokhin@gmail.com
Requires-Python: >=3.10,<4.0
Classifier: License :: OSI Approved :: MIT License
Classifier: Programming Language :: Python :: 3
Classifier: Programming Language :: Python :: 3.10
Classifier: Programming Language :: Python :: 3.11
Classifier: Programming Language :: Python :: 3.12
Requires-Dist: dacite (>=1.8.1,<2.0.0)
Requires-Dist: ffmpegio (>=0.10.0.post0,<0.11.0)
Requires-Dist: fire (>=0.6.0,<0.7.0)
Requires-Dist: humanize (>=4.10.0,<5.0.0)
Requires-Dist: numpy (>=2.0.1,<3.0.0)
Requires-Dist: pytest-cov (>=5.0.0,<6.0.0)
Requires-Dist: pyyaml (>=6.0.2,<7.0.0)
Requires-Dist: requests (>=2.32.3,<3.0.0)
Requires-Dist: scipy (>=1.14.0,<2.0.0)
Requires-Dist: tabulate (>=0.9.0,<0.10.0)
Requires-Dist: termcolor (>=2.4.0,<3.0.0)
Requires-Dist: tqdm (>=4.66.5,<5.0.0)
Project-URL: Repository, https://github.com/stepan-anokhin/audio-transformers
